lightning_cloud/__init__.py
lightning_cloud/__version__.py
lightning_cloud/env.py
lightning_cloud/login.py
lightning_cloud/rest_client.py
lightning_cloud/cli/__init__.py
lightning_cloud/openapi/__init__.py
lightning_cloud/openapi/api_client.py
lightning_cloud/openapi/configuration.py
lightning_cloud/openapi/rest.py
lightning_cloud/openapi/api/__init__.py
lightning_cloud/openapi/api/agent_service_api.py
lightning_cloud/openapi/api/analytics_service_api.py
lightning_cloud/openapi/api/assistants_service_api.py
lightning_cloud/openapi/api/auth_service_api.py
lightning_cloud/openapi/api/billing_service_api.py
lightning_cloud/openapi/api/blog_posts_service_api.py
lightning_cloud/openapi/api/cloud_space_environment_template_service_api.py
lightning_cloud/openapi/api/cloud_space_service_api.py
lightning_cloud/openapi/api/cloudy_service_api.py
lightning_cloud/openapi/api/cluster_service_api.py
lightning_cloud/openapi/api/data_connection_service_api.py
lightning_cloud/openapi/api/dataset_service_api.py
lightning_cloud/openapi/api/deployment_templates_service_api.py
lightning_cloud/openapi/api/endpoint_service_api.py
lightning_cloud/openapi/api/experiments_service_api.py
lightning_cloud/openapi/api/file_system_service_api.py
lightning_cloud/openapi/api/git_credentials_service_api.py
lightning_cloud/openapi/api/incidents_service_api.py
lightning_cloud/openapi/api/jobs_service_api.py
lightning_cloud/openapi/api/k8_s_cluster_service_api.py
lightning_cloud/openapi/api/lightningapp_instance_service_api.py
lightning_cloud/openapi/api/lightningapp_v2_service_api.py
lightning_cloud/openapi/api/lightningwork_service_api.py
lightning_cloud/openapi/api/lit_dataset_service_api.py
lightning_cloud/openapi/api/lit_logger_service_api.py
lightning_cloud/openapi/api/lit_page_service_api.py
lightning_cloud/openapi/api/lit_registry_service_api.py
lightning_cloud/openapi/api/markets_service_api.py
lightning_cloud/openapi/api/models_store_api.py
lightning_cloud-0.6.0.dist-info/LICENSE
lightning_cloud-0.6.0.dist-info/METADATA
lightning_cloud-0.6.0.dist-info/WHEEL
lightning_cloud-0.6.0.dist-info/top_level.txt
lightning_cloud-0.6.0.dist-info/RECORD
